[
    {
        "conversation_id": "conv_3150",
        "turns": [
            {
                "text": "So how do you feel about capital punishment",
                "label": "qo"
            },
            {
                "text": "Well its - I am pretty much against it",
                "label": "%"
            },
            {
                "text": "Really",
                "label": "qy"
            },
            {
                "text": "Yeah How about you",
                "label": "ny"
            },
            {
                "text": "Oh Im pretty much for it",
                "label": "sd"
            },
            {
                "text": "Oh good we can have debate",
                "label": "ba"
            },
            {
                "text": "Well have some interesting discussion I guess",
                "label": "sv"
            },
            {
                "text": "Well like um I dont know I - think that I - one of the reasons that Im against it is that uh um Im afraid of someone losing their life for - um wrongly",
                "label": "h"
            },
            {
                "text": "Wrongfully Yeah",
                "label": "^2"
            },
            {
                "text": "Right --",
                "label": "aa"
            },
            {
                "text": "Yeah",
                "label": "b"
            },
            {
                "text": "-- and uh another reason - one of the arguments that really I really actually have been kind of ambivalent about it but one of the arguments that really uh made me feel kind of strongly against it is that uh you know someone said to me once well imagine if the person you love most in the world like your mother or something if someone killed her wouldnt you want to see them killed for the punishment But then I thought about it and I thought well the loss that I would feel at losing my mother --",
                "label": "sd"
            },
            {
                "text": "Yeah it would never be equal",
                "label": "b"
            },
            {
                "text": "-- someone else would feel that about that person --",
                "label": "+"
            },
            {
                "text": "Right",
                "label": "b"
            },
            {
                "text": "-- no matter how rotten they were somebody loves them",
                "label": "+"
            },
            {
                "text": "Right Yeah",
                "label": "b"
            },
            {
                "text": "How about you",
                "label": "qo"
            },
            {
                "text": "Well I guess you know I I guess I can see it from several different perspectives but you know when I hear about things like you know what theyve what theyve been reporting about in Milwaukee you know I I to me I dont see any way of rehabilitating the guy You know maybe there is I dont know",
                "label": "h"
            },
            {
                "text": "Yeah thats true",
                "label": "b"
            },
            {
                "text": "But you know and you know hes never going to be to me functioning part of society Hes already been either paroled or whatever for child molestation",
                "label": "sv"
            },
            {
                "text": "Uh-hum",
                "label": "b"
            },
            {
                "text": "I mean I dont know I just I really have hard time with that because he really sounds like real sicko And you know for the things hes done I dont know I guess its either you know put him in jail for the rest of his life you know or or capital punishment I guess You know",
                "label": "h"
            },
            {
                "text": "Right Well you know",
                "label": "b"
            },
            {
                "text": "an- and-",
                "label": "%@"
            },
            {
                "text": "thats true because um - - lot of um these conversations Ive had on this program this",
                "label": "+"
            },
            {
                "text": "uh-huh",
                "label": "+@"
            },
            {
                "text": "these telephone conversations have revolved around um criminal",
                "label": "+"
            },
            {
                "text": "Oh really",
                "label": "b"
            },
            {
                "text": "you know justice uh-huh uh-huh Or whatever and most of the time I hear myself saying well you know we dont have enough room left in the jails and people crime is still climbing and we need to have different punishments you know",
                "label": "+"
            },
            {
                "text": "Right",
                "label": "b"
            },
            {
                "text": "but I just am scared of capital punishment",
                "label": "sd"
            },
            {
                "text": "Yeah",
                "label": "b@"
            },
            {
                "text": "I guess",
                "label": "+"
            },
            {
                "text": "Well I can underst- - I I mean you know there there is always that chance but you know I guess to some people itd almost be better to die to them than to spend life in prison or whatever I dont I mean I dont know but uh you know but that would be situation where if somebody you know was gonna be you know - you you you really throw lot on the courts hopefully that they wont do that you know for any for any situation really But uh you know when I you find somebody just like that situation I mean it was disgusting when I read about it today And and when you find someone like that that you know is guilty he confessed already to killing eleven --",
                "label": "+@"
            },
            {
                "text": "uh-huh",
                "label": "b"
            },
            {
                "text": "-- I Id you know I guess I have hard time feeling merciful toward him and --",
                "label": "+"
            },
            {
                "text": "Right",
                "label": "b"
            },
            {
                "text": "-- you know",
                "label": "+@"
            },
            {
                "text": "Especially when its so far removed If its no one that I know --",
                "label": "^2"
            },
            {
                "text": "Right",
                "label": "+@"
            },
            {
                "text": "-- then you have to think about the taxpayers paying --",
                "label": "+"
            },
            {
                "text": "Right",
                "label": "b"
            },
            {
                "text": "-- the shelter and feed and clothe --",
                "label": "+"
            },
            {
                "text": "Right",
                "label": "b"
            },
            {
                "text": "-- them for the rest of their life",
                "label": "+"
            },
            {
                "text": "And trying to rehabilitate him too and you know -",
                "label": "sv"
            },
            {
                "text": "Letting him out again",
                "label": "^2"
            },
            {
                "text": "Right exactly And uh you know nobody wants that",
                "label": "b"
            },
            {
                "text": "uh-huh",
                "label": "b"
            },
            {
                "text": "You know everybody would be just as scared to death you know We weve had real problem here in Texas with uh prison overcrowding and theyve been releasing people left and right and you know theyve committed murders and rapes and everything else and you know you just think you know wheres the justice here",
                "label": "sv"
            },
            {
                "text": "uh-huh",
                "label": "b"
            },
            {
                "text": "I mean you know theyre not even having to serve out what they should be serving",
                "label": "sv"
            },
            {
                "text": "Thats true You know I just recently moved to Massachusetts Im not sure what their policy is on capital punishment and that was one of the questions but uh I do know that they are notorious for paroling people",
                "label": "ba"
            },
            {
                "text": "Oh really",
                "label": "bh"
            },
            {
                "text": "Yeah when theyre when - and then having them reconvicted for --",
                "label": "ny"
            },
            {
                "text": "uh-huh",
                "label": "b"
            },
            {
                "text": "-- violent crimes",
                "label": "+"
            },
            {
                "text": "Yeah",
                "label": "b"
            },
            {
                "text": "And I guess they said you know sh- do you think it should be restricted I guess if it were if if - because lot of states do still practice capital punishment --",
                "label": "sd^2"
            },
            {
                "text": "uh-huh",
                "label": "b"
            },
            {
                "text": "-- I guess violent crimes would be the crimes where I can see it making the most sense",
                "label": "sv"
            },
            {
                "text": "Yeah",
                "label": "b"
            },
            {
                "text": "You know violent crimes with no uh with just malicious intent",
                "label": "sv"
            },
            {
                "text": "Right exactly Yeah Well you know thats exactly I mean Im Im not saying I I think capital murder or capital punishment is the perfect solution in every case you know especially because there are some cases when you just dont know and I I think theres shadow of doubt you know like with this this guy in in Milwaukee I mean it - he pretty much confessed to it I mean they you know - just everything I mean cannibalism and everything else uh",
                "label": "b"
            },
            {
                "text": "Yeah",
                "label": "b"
            },
            {
                "text": "I really would have hard time especially if I was on jury not wanting him to you know be executed",
                "label": "sd@"
            },
            {
                "text": "Hang",
                "label": "^2"
            },
            {
                "text": "Yeah Because I mean thats just awful",
                "label": "+@"
            },
            {
                "text": "And what is he going to do prison to the other people",
                "label": "bh"
            },
            {
                "text": "Right Well I have hun- I have hunch that you know the other prisoners arent going to be too happy with him anyway Either I mean you know they - I dont know from from what I hear about jail life is not any way to live",
                "label": "b"
            },
            {
                "text": "Right",
                "label": "b"
            },
            {
                "text": "But uh I dont know Its just -",
                "label": "%"
            },
            {
                "text": "Well I was I saw on human interest story or whatever today there was woman who was just being paroled and trying to make it back she --",
                "label": "sd"
            },
            {
                "text": "uh-huh",
                "label": "b"
            },
            {
                "text": "-- was off drugs and everything but she said uh you know in prison you can get anything You can any drugs you want Theres - it its just like being outside You know people --",
                "label": "+"
            },
            {
                "text": "Really",
                "label": "b"
            },
            {
                "text": "-- find ways around And theres power structure that you have bow to and and it really isnt for some people tha- who have been there for over and over and over it really isnt uh as bad I mean theres - its not that bad of life as it should be --",
                "label": "+"
            },
            {
                "text": "Yeah",
                "label": "b"
            },
            {
                "text": "-- - for the punishment aspect",
                "label": "+"
            },
            {
                "text": "Yeah",
                "label": "b"
            },
            {
                "text": "But the society is turned against punishment and more towards rehabilitation and --",
                "label": "sv"
            },
            {
                "text": "Yeah That -",
                "label": "b"
            },
            {
                "text": "-- maybe thats why one of the reasons why crime has gone up because its not so scary anymore",
                "label": "+"
            },
            {
                "text": "Yeah Well you know especially like repeat offenders It it just appalls me that they can be out you know they even get ten year sentence and be out in in two or three or four years You know thats thats scary because you know Im not sure I think were paroling them without even knowing if theyre you know going to be committing any more violent acts or not",
                "label": "b"
            },
            {
                "text": "Right And what theyre going to be doing when they --",
                "label": "b"
            },
            {
                "text": "Right",
                "label": "b"
            },
            {
                "text": "-- get out",
                "label": "+"
            },
            {
                "text": "And it its its really scary I me- you know - I I dont know what the perfect solution to that is but I know that especially with violent crimes where you know youre nearly hundred percent convinced that theyre guilty and without much repentance or anything else you know then I dont know I I guess I I just really dont see much use for this guy in Milwaukee you know For instance I mean thats just - I could see capital punishment in case like that And you know for for other people too that do things like that But uh when - uh my wife and I are both participating in this survey and she picked up the phone and when she heard the topic she said capital punishment so she was uh -",
                "label": "sv"
            },
            {
                "text": "Handed it to you",
                "label": "qy^d"
            },
            {
                "text": "Yeah well luckily it was for me Because they want th- they coordinate the times so it can only be one or the other",
                "label": "ny"
            },
            {
                "text": "Oh oh I see",
                "label": "b"
            },
            {
                "text": "So she tried to enter her number and it wouldnt work so she said whew its for you So but uh you know I dont know I I struggle with it but I I really think that in in terms of like this Id I think that it it might not be such bad thing Because I dont know that anybody - in- I dont know that anybody would feel good you know like if you let someone like that loose in your community You know I I Im su- - youd have to be scared to death",
                "label": "sd^t"
            },
            {
                "text": "Well maybe if they could uh - if they had more money or more more resources to work more on rehabilitation - I mean deep down I think every every human -",
                "label": "sv"
            }
        ]
    }
]