[
    {
        "conversation_id": "conv_4821",
        "turns": [
            {
                "text": "Okay Uh let me see Ive been sitting here awhile I almost forgot the topic But uh it seems like I get most of my news from television Im we only get the paper on the weekends and so Im not much of of paper reader or but I I and Im dont rarely listen to the uh radio so I get most of my news like from documentaries like FORTY-EIGHT HOURS TWENTY TWENTY you know the news at night",
                "label": "o"
            },
            {
                "text": "uh-huh",
                "label": "b"
            },
            {
                "text": "News in the afternoon that kind of thing",
                "label": "+"
            },
            {
                "text": "uh-huh Well I get weekend paper as well and uh in addition to that I get local weekly I I live in suburb of Milwaukee --",
                "label": "b"
            },
            {
                "text": "uh-huh",
                "label": "b"
            },
            {
                "text": "-- and they get they have community newspapers around here so the local their extremely local stuff --",
                "label": "sd"
            },
            {
                "text": "uh-huh",
                "label": "b"
            },
            {
                "text": "-- uh is in the local paper that comes out once week and then I get the Sunday uh MILWAUKEE JOURNAL because I dont have time to read paper Uh mostly --",
                "label": "+"
            },
            {
                "text": "Right",
                "label": "b"
            },
            {
                "text": "-- thats my difficulty I uh I get my news pretty much from the same sources as you do although I do listen to which has very good and thats National Public Radio which --",
                "label": "+"
            },
            {
                "text": "uh-huh",
                "label": "b"
            },
            {
                "text": "-- has very good uh coverage of the national and international news I feel --",
                "label": "+"
            },
            {
                "text": "uh-huh",
                "label": "b"
            },
            {
                "text": "-- and does pretty good job of analysis as well",
                "label": "+"
            },
            {
                "text": "Are you in the car quite bit or -",
                "label": "qy"
            },
            {
                "text": "No Im not actually Uh but I can run my radio in my office I I --",
                "label": "nn"
            },
            {
                "text": "Oh",
                "label": "b"
            },
            {
                "text": "-- teach at the university and when Im not --",
                "label": "+"
            },
            {
                "text": "Oh",
                "label": "b"
            },
            {
                "text": "-- teaching if I choose to have the radio on I can listen to that station so -",
                "label": "+"
            },
            {
                "text": "uh-huh Oh I see Uh",
                "label": "b"
            },
            {
                "text": "How are you are you satisfied with the TWENTY TWENTY and FORTY-EIGHT HOURS and the things that you do watch",
                "label": "qy"
            },
            {
                "text": "Yeah I I I pretty much am and I watch the news at least twice day",
                "label": "ny"
            },
            {
                "text": "uh-huh",
                "label": "b"
            },
            {
                "text": "So uh if Ive missed something and and Ive just recently decided to stay home with my children and so it seems as if I catch the news ris- right as it happens you know",
                "label": "sd"
            },
            {
                "text": "uh-huh",
                "label": "b"
            },
            {
                "text": "There was the explosions and that kind of thing My husband will say how did you know about that Yes it happened at such and such time And thats so that thats different for me So I usually find out exactly when it happens and that kind of thing",
                "label": "sd"
            },
            {
                "text": "Is that the aspect of the news that youre most interested in is is the timely yo- noting of the events as they happen Is that what you feel good about in the news coverage",
                "label": "qy"
            },
            {
                "text": "Uh no it just seems like since Ive recently stayed home that is whats happened you know Its just that uh now that Ive stayed home Im Im usually aware of when these things occurred --",
                "label": "nn"
            },
            {
                "text": "uh-huh",
                "label": "b"
            },
            {
                "text": "-- and it happened and -",
                "label": "sd"
            },
            {
                "text": "Well I myself uh th- the reason why I listen to and the reason why I watch MACNEIL LEHRER rather than the than the network news shows at night although I do - watch local ten oclock in the evening news which carries over lot of the national news stories --",
                "label": "sd"
            },
            {
                "text": "Right right",
                "label": "b"
            },
            {
                "text": "-- uh is that quite often it seems to me the national doesnt do very good job of analysis The local doesnt either but I feel that MACNEIL LEHRER get little more deeply into some some of the issues that are really current",
                "label": "+"
            },
            {
                "text": "uh-huh slash unit plus is this considered non-speech",
                "label": "b"
            },
            {
                "text": "And perhaps newspapers do that but as I said I dont have time to sit down and read newspaper and frankly when I have read newspaper --",
                "label": "sv"
            },
            {
                "text": "uh-huh",
                "label": "b"
            },
            {
                "text": "-- I havent noticed that kind of analysis either",
                "label": "+"
            },
            {
                "text": "Huh",
                "label": "b"
            },
            {
                "text": "So Uh theres there is some danger to that of course too Because if the analysis is inaccurate or biased or whatever then you know how good is it But uh I like little more indepth coverage and I think thats what youre maybe appealing to you too on something like TWENTY TWENTY or --",
                "label": "sv"
            },
            {
                "text": "Right",
                "label": "aa"
            },
            {
                "text": "-- FORTY-EIGHT HOURS",
                "label": "+"
            },
            {
                "text": "Right It kind of gives you the whole story or more of the story",
                "label": "aa"
            },
            {
                "text": "uh-huh",
                "label": "b"
            },
            {
                "text": "That kind of thing",
                "label": "h"
            },
            {
                "text": "Yeah",
                "label": "b"
            },
            {
                "text": "So Uh -",
                "label": "%"
            },
            {
                "text": "Im more interested in trying to understand whats going on in the world --",
                "label": "sd"
            },
            {
                "text": "Yeah",
                "label": "b"
            },
            {
                "text": "-- rather than simply being aware that you know there that an event has occurred",
                "label": "+"
            },
            {
                "text": "Yeah",
                "label": "b"
            },
            {
                "text": "I I like to stand back and get slightly bigger picture Maybe because Im easily confused by detail I dont know",
                "label": "sd"
            },
            {
                "text": "uh-huh Yeah I know what youre saying Yeah",
                "label": "b"
            },
            {
                "text": "So -",
                "label": "%"
            },
            {
                "text": "But I try and catch most of those programs on Wednesdays and Fridays and if I miss them I try you know I try and and tape them if Im out that kind of thing I try and tape them and so I can sit back and watch them And its pretty interesting",
                "label": "sd"
            },
            {
                "text": "When - you have young children right",
                "label": "%"
            },
            {
                "text": "uh-huh",
                "label": "ny"
            },
            {
                "text": "So those evening shows are probably also at time when youre at liberty to take some time off and be in front of the set for awhile without interruption",
                "label": "qy^d"
            },
            {
                "text": "Well yeah Plus I find that I have to video tape quite bit of things",
                "label": "ny"
            },
            {
                "text": "Oh you do uh-huh",
                "label": "bh"
            },
            {
                "text": "If I dont want any interruptions you know",
                "label": "sd"
            },
            {
                "text": "uh-huh",
                "label": "b"
            },
            {
                "text": "That kind of thing",
                "label": "h"
            },
            {
                "text": "When is your good watching time",
                "label": "qw"
            },
            {
                "text": "Uh it seems like ten oclock at night",
                "label": "sd"
            },
            {
                "text": "uh-huh Yes Yeah thats what -",
                "label": "b"
            },
            {
                "text": "Unfortunately but that thats what it seems like ten oclock at night",
                "label": "sd"
            },
            {
                "text": "I have older children --",
                "label": "sd"
            },
            {
                "text": "uh-huh",
                "label": "b"
            },
            {
                "text": "-- and getting dinner on the table I come from the east coast and I was - it amazed me when I got out here to the midwest and found out that even though theyre an hour earlier in time they still watch the news when -",
                "label": "+"
            }
        ]
    }
]