[
    {
        "conversation_id": "conv_4443",
        "turns": [
            {
                "text": "Do you play",
                "label": "qy"
            },
            {
                "text": "Yeah I uh consider myself hacker How about you",
                "label": "ny"
            },
            {
                "text": "Oh yeah Is that really question mark on what appears to be an answer Well Im into it Uh",
                "label": "ny@"
            },
            {
                "text": "Yeah uh Im not as good as Id like to be but its -",
                "label": "b"
            },
            {
                "text": "Is anybody",
                "label": "qy"
            },
            {
                "text": "No I dont think so Uh Id started playing when I was in elementary school actually We lived --",
                "label": "nn"
            },
            {
                "text": "Really",
                "label": "bh"
            },
            {
                "text": "-- really close to par three golf course And Id go up there with friends after school couple of times every week and then --",
                "label": "+"
            },
            {
                "text": "Oh wow",
                "label": "ba"
            },
            {
                "text": "-- for uh for years I dont know after elementary school all through junior high and stuff I didnt play cause I think I just got so frustrated when I was little Id my body wasnt you know --",
                "label": "+"
            },
            {
                "text": "Right",
                "label": "b"
            },
            {
                "text": "-- physically developed and all that kind of stuff and then Id started picking it up again couple of years back and Ive really been enjoying it",
                "label": "+"
            },
            {
                "text": "Super Yeah thats kind of the way I did it too actually I I played uh just tiny bit when I was real young and then uh I - I got on to team in high school but wasnt very good still",
                "label": "ba"
            },
            {
                "text": "uh-huh",
                "label": "b"
            },
            {
                "text": "But and then quit for awhile and recently I picked it up like you say about couple of years ago and uh Ive been playing you know off and on when I can",
                "label": "+"
            },
            {
                "text": "Right",
                "label": "b"
            },
            {
                "text": "Up in Minneapolis its not too easy to play in the winter of course --",
                "label": "sd"
            },
            {
                "text": "uh-huh",
                "label": "b"
            },
            {
                "text": "-- but I actually live in Florida so uh --",
                "label": "sd"
            },
            {
                "text": "uh-huh",
                "label": "b"
            },
            {
                "text": "-- uh Ill be going back down there in May and hopefully be picking it up little more regularly",
                "label": "+"
            },
            {
                "text": "Right Th- - the one factor that really bothers me is the expense of playing golf",
                "label": "b"
            },
            {
                "text": "I was going to say",
                "label": "aa"
            },
            {
                "text": "I mean its great game but I mean to play really nice course youve got to have really big wallet I mean",
                "label": "sv"
            },
            {
                "text": "Yeah thats thats true all too many times",
                "label": "aa"
            },
            {
                "text": "Yeah",
                "label": "b"
            },
            {
                "text": "Fortunately uh down where I live in Florida theres some golf courses that are pretty reasonable if you know where to look",
                "label": "sd"
            },
            {
                "text": "uh-huh",
                "label": "b"
            },
            {
                "text": "Uh one of them is the University of Florida golf course --",
                "label": "sd"
            },
            {
                "text": "Right",
                "label": "b"
            },
            {
                "text": "-- which is open to the public and thats pretty pretty good",
                "label": "+"
            },
            {
                "text": "Yeah I uh attend the Indiana University and its the same way here They have really nice championship style course that --",
                "label": "b"
            },
            {
                "text": "Yeah",
                "label": "b"
            },
            {
                "text": "-- is fairly reasonable to play on",
                "label": "+"
            },
            {
                "text": "Can you get like student discount type of thing or -",
                "label": "qy"
            },
            {
                "text": "Uh little bit but not whole lot I mean I youd think you would but uh you dont so I -",
                "label": "na"
            },
            {
                "text": "Yeah What what what are green fees run there",
                "label": "b"
            },
            {
                "text": "Uh well they range anywhere from about five bucks for your basic city type course up to fifty sixty dollars for really really nice course",
                "label": "sd"
            },
            {
                "text": "Okay Thats - yeah thats about the same I guess as it is in Florida But -",
                "label": "bk"
            },
            {
                "text": "uh-huh My dad is member of golf club over in my home town and I can play for free there and its pretty nice course",
                "label": "b"
            },
            {
                "text": "Really Oh thats super",
                "label": "b"
            },
            {
                "text": "Yeah And I guess well its free for me",
                "label": "aa"
            },
            {
                "text": "Yeah uh-huh",
                "label": "b"
            },
            {
                "text": "Somebodys paying but not me",
                "label": "sd"
            },
            {
                "text": "Well thats the way to do it though",
                "label": "ba"
            },
            {
                "text": "Yeah",
                "label": "aa"
            },
            {
                "text": "Thats the way to get in some good practice without having to pay for it all the time",
                "label": "sv"
            },
            {
                "text": "Yeah definitely As far as watching golf I mean I can watch it on but its kind of boring",
                "label": "aa"
            },
            {
                "text": "Yeah",
                "label": "b"
            },
            {
                "text": "Its nice to see those who guys They have such good style that uh --",
                "label": "sv"
            },
            {
                "text": "Yeah",
                "label": "b"
            },
            {
                "text": "-- its uh its pretty fun to watch",
                "label": "+"
            },
            {
                "text": "They need to get new photography method Because once the guy hits the ball and they got to try to follow the ball --",
                "label": "sv"
            },
            {
                "text": "Right Yeah",
                "label": "aa"
            },
            {
                "text": "-- thats thats little difficult I mean it they do they do generally okay job but like you said its its kind of boring actually",
                "label": "+"
            },
            {
                "text": "uh-huh What I really - I uh had chance - they had the tournament up in Indianapolis last year --",
                "label": "b"
            },
            {
                "text": "Oh yeah",
                "label": "bh"
            },
            {
                "text": "-- and I was able to go and see one of the rounds of that and that was really fun I mean you knew it --",
                "label": "sd"
            },
            {
                "text": "Yeah I bet that would be -",
                "label": "aa"
            },
            {
                "text": "-- I never really thought it was would be that much fun to go to big golf tournament and watch but man it was it was something else just to follow those guys around and actually watch them play",
                "label": "sd"
            },
            {
                "text": "Yeah Yeah Ive never been to tournament Uh you know looking at it on youre thinking man what boring thing you know",
                "label": "b"
            },
            {
                "text": "Right",
                "label": "aa"
            },
            {
                "text": "But uh thats thats wild though Ill have to see if I cant get chance --",
                "label": "sv"
            },
            {
                "text": "You got -- -",
                "label": "%"
            },
            {
                "text": "-- to go",
                "label": "+"
            },
            {
                "text": "-- I mean its uh its lot more exciting than actually - than watching it on And if you pick group of golfers and follow them around I mean its just watching them the whole time instead of like on you get to see them make tee shot --",
                "label": "sd"
            },
            {
                "text": "Right",
                "label": "b"
            },
            {
                "text": "-- and then they go off to some other hole and they come back when theyre putting but you know its really something else",
                "label": "sd"
            },
            {
                "text": "Yeah I can imagine What do you do for living",
                "label": "b"
            },
            {
                "text": "Uh Im student right now",
                "label": "sd"
            },
            {
                "text": "Oh you are",
                "label": "bh"
            },
            {
                "text": "Yeah",
                "label": "ny"
            },
            {
                "text": "Which uh which university",
                "label": "qw"
            },
            {
                "text": "At uh Indiana University",
                "label": "sd"
            },
            {
                "text": "Okay All right great What are you going into",
                "label": "bk"
            },
            {
                "text": "Uh I dont really know Im math computer science major right now",
                "label": "sd"
            },
            {
                "text": "Okay Definitely not golf right",
                "label": "bk"
            },
            {
                "text": "No I wi- - itd be nice to be pro golfer I mean it seems like that that would be an okay life just to hang out and -",
                "label": "nn"
            },
            {
                "text": "Yeah If youre good you can really rake in the bucks Wh- - what was --",
                "label": "aa"
            },
            {
                "text": "Yeah",
                "label": "b"
            },
            {
                "text": "-- what was that movie that they had out Th- - there was movie about professional golfer and I I --",
                "label": "+"
            },
            {
                "text": "Huh",
                "label": "b"
            },
            {
                "text": "-- cant remember It was on network couple of times",
                "label": "+"
            },
            {
                "text": "Oh yeah",
                "label": "bh"
            },
            {
                "text": "Yeah",
                "label": "ny"
            },
            {
                "text": "Well you know it seems like well you go to work every weekend Play maybe one two tournaments month You come in about tenth youd still --",
                "label": "sv"
            },
            {
                "text": "Thats right",
                "label": "aa"
            },
            {
                "text": "-- be doing pretty well So -",
                "label": "+"
            },
            {
                "text": "Yeah thats good thing",
                "label": "aa"
            },
            {
                "text": "Yeah",
                "label": "b"
            },
            {
                "text": "But uh yeah I guess when I get back Im going to school in Florida actually Uh and fortunately Ive been able to to play some golf on student budget which is --",
                "label": "b"
            },
            {
                "text": "uh-huh",
                "label": "b"
            },
            {
                "text": "-- real helpful you know But it its unfortunate you know You hear about Japan",
                "label": "+"
            },
            {
                "text": "Right",
                "label": "b"
            },
            {
                "text": "I guess you know its its like two hundred fifty dollar minimum or three hundred dollar minimum just to like to practice even",
                "label": "+"
            },
            {
                "text": "Yeah And those fees to join club Like million dollars or whatever is just -- -",
                "label": "b"
            },
            {
                "text": "Yeah",
                "label": "b"
            },
            {
                "text": "-- that is out of control I mean youd really want to really be liking your golf",
                "label": "sv"
            },
            {
                "text": "Yeah I guess they have those uh driving ranges that are actually stacked one on top of the other",
                "label": "aa"
            },
            {
                "text": "Yeah I saw one of those on That is pretty wild",
                "label": "b"
            },
            {
                "text": "Yeah Yeah I I played uh uh eighteen holes with some Japanese guys in in Gainesville as matter of fact And it was really wild They were into it",
                "label": "b"
            },
            {
                "text": "Yeah",
                "label": "b"
            },
            {
                "text": "You know they kicked our butt all the way to -",
                "label": "sd"
            }
        ]
    }
]