[
    {
        "conversation_id": "conv_3883",
        "turns": [
            {
                "text": "Okay So how do you just figure -",
                "label": "o"
            },
            {
                "text": "Well you know it depends upon our weather here You know today was beautiful day it was like uh uh summer day It was seventy degrees so --",
                "label": "sd"
            },
            {
                "text": "Wow",
                "label": "ba"
            },
            {
                "text": "-- so I dressed in uh uh light weight skirt its uh ultra suede skirt and blouse with sweater cardigan --",
                "label": "+"
            },
            {
                "text": "uh-huh",
                "label": "b"
            },
            {
                "text": "-- over it Because I had some appointments at the office today some interviews and so I had to dress up anyway and then I wore heels you know",
                "label": "+"
            },
            {
                "text": "uh-huh",
                "label": "b"
            },
            {
                "text": "But when it rains lot which is has been doing here lot lately uh very often you know wear uh pants and boots --",
                "label": "sd"
            },
            {
                "text": "Oh",
                "label": "b"
            },
            {
                "text": "-- you know So how do you dress",
                "label": "+"
            },
            {
                "text": "Well um Im going to talk about when I was working as teacher and when I was working at now",
                "label": "co"
            },
            {
                "text": "Okay",
                "label": "aa"
            },
            {
                "text": "Um when I was teacher um in Utah I would generally wear um dresses and heels and things like that",
                "label": "sd"
            },
            {
                "text": "uh-huh",
                "label": "b"
            },
            {
                "text": "and even when it um rained and snowed I just braved it and I wore heels anyway",
                "label": "sd"
            },
            {
                "text": "Yeah",
                "label": "b"
            },
            {
                "text": "And -",
                "label": "%"
            },
            {
                "text": "I I can see - I Ive been teacher so has my daughter and I know that we very often wore heels despite the fact that",
                "label": "sd"
            },
            {
                "text": "I know",
                "label": "aa"
            },
            {
                "text": "it was tiring",
                "label": "+"
            },
            {
                "text": "it might kill you to go up and",
                "label": "bf"
            },
            {
                "text": "Thats right",
                "label": "aa"
            },
            {
                "text": "walk up to the door but youre going to look nice for the kids",
                "label": "+"
            },
            {
                "text": "Thats right and it always makes you feel like youre bigger person than the kids right",
                "label": "aa"
            },
            {
                "text": "Oh oh yeah Well I need all the height I can get",
                "label": "aa"
            },
            {
                "text": "Yeah I do too So to be taller than some of the boys in the bigger grades",
                "label": "aa"
            },
            {
                "text": "Oh yeah",
                "label": "aa"
            },
            {
                "text": "uh older grades I had to wear heels",
                "label": "+"
            },
            {
                "text": "uh-huh Yeah we too Um if it was real- it looked really dangerous then I would wear boots but then I would change um into heels",
                "label": "aa"
            },
            {
                "text": "uh-huh",
                "label": "b"
            },
            {
                "text": "as soon as I got to my desk So um -",
                "label": "+"
            },
            {
                "text": "Of course we wear uh an unlined boots you know it has heel on it Theyre the kind of boots that I wear to work and we wear them you know theyre leather boot that you wear and as I said they have regular heel on them high heel",
                "label": "sd"
            },
            {
                "text": "Oh",
                "label": "b"
            },
            {
                "text": "And they wear them we wear them lot with shirts and things Uh its kind of - I cant say constant down here in Texas that you wear these boots - Theyre not cowboy boot but theyre just real pretty boot but they keep your feet nice and toasty from the rain",
                "label": "sd"
            },
            {
                "text": "Oh",
                "label": "b"
            },
            {
                "text": "As I have private high school that I run here and so when Im interviewing parent of course I feel like I need to wear heels --",
                "label": "sd(^q)"
            },
            {
                "text": "Sure uh-huh",
                "label": "b"
            },
            {
                "text": "-- you know and look like Im business person",
                "label": "+"
            },
            {
                "text": "uh-huh Yeah",
                "label": "b"
            },
            {
                "text": "You know because the children will tease about wheres your motorcycle if you wear boots too often you know",
                "label": "+"
            },
            {
                "text": "Huh Well um -",
                "label": "%"
            },
            {
                "text": "Of course you probably wear coats lot",
                "label": "sv"
            },
            {
                "text": "Yeah um the first two years I was in room where they didnt heat it So I did -",
                "label": "aa"
            },
            {
                "text": "Oh my goodness so then you had to",
                "label": "ba"
            },
            {
                "text": "Yeah and then the third year we um got heating so it was nice",
                "label": "aa"
            },
            {
                "text": "Yes Then things improved right",
                "label": "aa"
            },
            {
                "text": "Right uh-huh",
                "label": "na"
            },
            {
                "text": "But of course here we wear light weight jacket lot you know you know",
                "label": "sd"
            },
            {
                "text": "Oh thats nice",
                "label": "ba"
            },
            {
                "text": "and uh thats very seldom we it depends upon our winter We have few days you might wear coat winter coat you know but most of the time you can wear sweater and we just dont wear coats much We often laugh about even when it turns chilly Were wearing something lightweight or no jacket because were so used to running around like that",
                "label": "sd"
            },
            {
                "text": "uh-huh Oh Nice Well -",
                "label": "b"
            },
            {
                "text": "Its really different Lets put it that way Are you not teaching anymore",
                "label": "sd"
            },
            {
                "text": "Uh no we we moved to Iowa and um Im working at day care right now",
                "label": "nn"
            },
            {
                "text": "I see",
                "label": "bk"
            },
            {
                "text": "And so the way I dress is really different because Im working in the nursery room with kids from six months to like twenty months",
                "label": "sd"
            },
            {
                "text": "Oh so you dont wear heels anymore Ill bet",
                "label": "bf"
            },
            {
                "text": "Yeah I wear uh tennis shoes",
                "label": "aa"
            },
            {
                "text": "Yeah uh-huh",
                "label": "b"
            },
            {
                "text": "and jeans and things that you know are sort of um -",
                "label": "+"
            },
            {
                "text": "More practical",
                "label": "^2"
            },
            {
                "text": "not - yes it doesnt matter if I have to wash it hundred times or something",
                "label": "%"
            },
            {
                "text": "When you were teaching did you ever have uh uh blue jean day or anything like that",
                "label": "qy"
            },
            {
                "text": "Yeah but I never wore jeans because um I thought that was too casual",
                "label": "ny"
            },
            {
                "text": "Yeah well",
                "label": "b"
            },
            {
                "text": "For -",
                "label": "%"
            },
            {
                "text": "I know that some of the schools they have uh country western day or something like that one you know or tacky day and I always thought it was kind of out of got out of hand when the teachers looked real tacky too",
                "label": "sd"
            },
            {
                "text": "Yeah really",
                "label": "aa"
            },
            {
                "text": "Its all right for the students they look tacky lot but I didnt think teachers should you know",
                "label": "sv"
            },
            {
                "text": "Yeah thats how I feel too",
                "label": "aa"
            },
            {
                "text": "Yeah Do you like uh uh Iowa",
                "label": "b"
            },
            {
                "text": "Um oh it theres some good things about it but Ive seen lot of things Im not used to yet um",
                "label": "nd"
            },
            {
                "text": "Where did you live before",
                "label": "qw"
            },
            {
                "text": "Um we lived in Utah before and and I grew up in California",
                "label": "sd"
            },
            {
                "text": "Oh well thats quite change from California to Utah",
                "label": "bf"
            }
        ]
    }
]